polypeptideclient/__init__.py
polypeptideclient/cli.py
polypeptideclient/polypeptideclient.py
polypeptideclient-0.2.3.dist-info/AUTHORS.rst
polypeptideclient-0.2.3.dist-info/LICENSE
polypeptideclient-0.2.3.dist-info/METADATA
polypeptideclient-0.2.3.dist-info/WHEEL
polypeptideclient-0.2.3.dist-info/entry_points.txt
polypeptideclient-0.2.3.dist-info/top_level.txt
polypeptideclient-0.2.3.dist-info/RECORD
