Metadata-Version: 2.1
Name: polypeptideclient
Version: 0.2.3
Summary: A HTTP client for the Polypeptide Webservices
Home-page: https://github.com/gusennan/polypeptideclient
Author: Nate Guerin
Author-email: nate@textpla.in
License: GNU General Public License v3
Keywords: polypeptideclient
Platform: UNKNOWN
Classifier: Development Status :: 2 - Pre-Alpha
Classifier: Intended Audience :: Developers
Classifier: License :: OSI Approved :: GNU General Public License v3 (GPLv3)
Classifier: Natural Language :: English
Classifier: Programming Language :: Python :: 3
Classifier: Programming Language :: Python :: 3.5
Classifier: Programming Language :: Python :: 3.6
Classifier: Programming Language :: Python :: 3.7
Classifier: Programming Language :: Python :: 3.8
Requires-Python: >=3.5
Requires-Dist: Click (>=7.0)
Requires-Dist: Requests (>=2.23)
